toplineauth/__init__.py
toplineauth/api/__init__.py
toplineauth/api/app_management/__init__.py
toplineauth/api/app_management/app_management_add_tenant_to_app.py
toplineauth/api/app_management/app_management_create_app.py
toplineauth/api/app_management/app_management_delete_app.py
toplineauth/api/app_management/app_management_get_app.py
toplineauth/api/app_management/app_management_get_app_tenants.py
toplineauth/api/app_management/app_management_list_apps.py
toplineauth/api/app_management/app_management_regenerate_api_key.py
toplineauth/api/app_management/app_management_remove_tenant_from_app.py
toplineauth/api/app_management/app_management_update_app.py
toplineauth/api/authentication/__init__.py
toplineauth/api/authentication/authentication_logout.py
toplineauth/api/authentication/authentication_refresh_access_token.py
toplineauth/api/authentication/authentication_verify_access_token.py
toplineauth/api/items/__init__.py
toplineauth/api/items/items_create_item.py
toplineauth/api/items/items_delete_item.py
toplineauth/api/items/items_read_item.py
toplineauth/api/items/items_read_items.py
toplineauth/api/items/items_update_item.py
toplineauth/api/login/__init__.py
toplineauth/api/login/login_login_access_token.py
toplineauth/api/login/login_recover_password.py
toplineauth/api/login/login_recover_password_html_content.py
toplineauth/api/login/login_reset_password.py
toplineauth/api/login/login_test_token.py
toplineauth/api/multi_tenant_auth/__init__.py
toplineauth/api/multi_tenant_auth/multi_tenant_auth_assign_user_roles.py
toplineauth/api/multi_tenant_auth/multi_tenant_auth_get_tenant_apps.py
toplineauth/api/multi_tenant_auth/multi_tenant_auth_get_user_roles.py
toplineauth/api/multi_tenant_auth/multi_tenant_auth_get_user_tenants.py
toplineauth/api/multi_tenant_auth/multi_tenant_auth_multi_tenant_login.py
toplineauth/api/multi_tenant_auth/multi_tenant_auth_multi_tenant_prelogin.py
toplineauth/api/multi_tenant_auth/multi_tenant_auth_multi_tenant_register.py
toplineauth-1.0.1.dist-info/METADATA
toplineauth-1.0.1.dist-info/WHEEL
toplineauth-1.0.1.dist-info/RECORD
