Metadata-Version: 2.4
Name: toplineauth
Version: 1.0.1
Summary: A client library for accessing Topline Multi-Tenant Auth
Author: WANG Lvyuan
Requires-Python: >=3.10,<4.0
Classifier: Programming Language :: Python :: 3
Classifier: Programming Language :: Python :: 3.10
Classifier: Programming Language :: Python :: 3.11
Classifier: Programming Language :: Python :: 3.12
Classifier: Programming Language :: Python :: 3.13
Classifier: Programming Language :: Python :: 3.14
Requires-Dist: attrs (>=22.2.0)
Requires-Dist: httpx (>=0.23.0,<0.29.0)
Requires-Dist: python-dateutil (>=2.8.0,<3.0.0)
